caoyizhen_basetool/__init__.py
caoyizhen_basetool/file/__init__.py
caoyizhen_basetool/file/utils.py
caoyizhen_basetool/process/__init__.py
caoyizhen_basetool/process/data_process.py
caoyizhen_basetool/process/multi_thread_process.py
caoyizhen_basetool/utils/__init__.py
caoyizhen_basetool/utils/log_manage.py
caoyizhen_basetool/utils/utils.py
caoyizhen_basetool-0.5.0.dist-info/METADATA
caoyizhen_basetool-0.5.0.dist-info/WHEEL
caoyizhen_basetool-0.5.0.dist-info/top_level.txt
caoyizhen_basetool-0.5.0.dist-info/RECORD
